z5_tracker-1.2.1.dist-info/DESCRIPTION.rst
z5_tracker-1.2.1.dist-info/METADATA
z5_tracker-1.2.1.dist-info/RECORD
z5_tracker-1.2.1.dist-info/WHEEL
z5_tracker-1.2.1.dist-info/entry_points.txt
z5_tracker-1.2.1.dist-info/metadata.json
z5_tracker-1.2.1.dist-info/top_level.txt
z5tracker/__init__.py
z5tracker/__main__.py
z5tracker/gui.py
z5tracker/main.py
z5tracker/version.py
z5tracker/config/__init__.py
z5tracker/config/config.py
z5tracker/config/default.py
z5tracker/config/globals.py
z5tracker/config/images.py
z5tracker/config/layout.py
z5tracker/config/windows.py
z5tracker/dungeons/__init__.py
z5tracker/dungeons/dungeonobj.py
z5tracker/dungeons/dungeons.py
z5tracker/dungeons/lists.py
z5tracker/gui-tkinter/__init__.py
z5tracker/gui-tkinter/config.py
z5tracker/gui-tkinter/dungeons.py
z5tracker/gui-tkinter/hints.py
z5tracker/gui-tkinter/interface.py
z5tracker/gui-tkinter/items.py
z5tracker/gui-tkinter/maps.py
z5tracker/gui-tkinter/menu.py
z5tracker/gui-tkinter/misc.py
z5tracker/hints/__init__.py
z5tracker/hints/hints.py
z5tracker/images/HC.png
z5tracker/images/HP.png
z5tracker/images/agony.png
z5tracker/images/bean.png
z5tracker/images/bluetunic.png
z5tracker/images/bolero.png
z5tracker/images/bomb.png
z5tracker/images/bombchu.png
z5tracker/images/boomerang.png
z5tracker/images/boots.png
z5tracker/images/bosskey.png
z5tracker/images/bottle.png
z5tracker/images/bottle_bigpoe.png
z5tracker/images/bottle_blue.png
z5tracker/images/bottle_bugs.png
z5tracker/images/bottle_fairy.png
z5tracker/images/bottle_fire.png
z5tracker/images/bottle_fish.png
z5tracker/images/bottle_green.png
z5tracker/images/bottle_halfmilk.png
z5tracker/images/bottle_letter.png
z5tracker/images/bottle_milk.png
z5tracker/images/bottle_poe.png
z5tracker/images/bottle_red.png
z5tracker/images/bow.png
z5tracker/images/broken_sword.png
z5tracker/images/bunny.png
z5tracker/images/chest_brown_closed.png
z5tracker/images/chest_brown_open.png
z5tracker/images/chest_golden_closed.png
z5tracker/images/chest_golden_open.png
z5tracker/images/claim.png
z5tracker/images/cojiro.png
z5tracker/images/cucco.png
z5tracker/images/deku_scrub.png
z5tracker/images/din.png
z5tracker/images/dungeon_dekutree.png
