Metadata-Version: 2.0
Name: z5-tracker
Version: 1.2.1
Summary: Helper program for Ocarina of Time randomiser
Home-page: https://www.github.com/feneg/z5-tracker
Author: Feneg
Author-email: UNKNOWN
License: UNKNOWN
Platform: UNKNOWN
Classifier: Development Status :: 4 - Beta
Classifier: License :: OSI Approved :: MIT License
Classifier: Programming Language :: Python :: 3.6
Classifier: Topic :: Games/Entertainment
Classifier: Topic :: Utilities
